README.md
setup.cfg
setup.py
vna_cals/Mixer.py
vna_cals/NIBlock.py
vna_cals/__init__.py
vna_cals/config.py
vna_cals/logger.py
vna_cals/main.py
vna_cals/scpi.py
vna_cals/test.py
vna_cals/utils.py
vna_cals/vna.py
vna_cals.egg-info/PKG-INFO
vna_cals.egg-info/SOURCES.txt
vna_cals.egg-info/dependency_links.txt
vna_cals.egg-info/not-zip-safe
vna_cals.egg-info/top_level.txt