Metadata-Version: 1.0
Name: vna-cals
Version: 0.13
Summary: SIS Mixing
Home-page: UNKNOWN
Author: UNKNOWN
Author-email: yarvodd@gmail.com
License: UNKNOWN
Platform: UNKNOWN
